{
  "name": "ant-game",
  "tree": {
    "$className": "DataModel",

    "ReplicatedStorage": {
		"$className": "ReplicatedStorage",
		"$ignoreUnknownInstances": true,
		"$path": "src/shared",

	  "Assets": {
		"$className": "Folder",
		"$path": "assets/ReplicatedStorage"
		}
    },

    "ServerScriptService": {
      "Server": {
        "$path": "src/server"
      }
    },

    "StarterPlayer": {
      "StarterPlayerScripts": {
        "Client": {
          "$path": "src/client"
        }
      }
    },

	"Workspace": {
		"$className": "Workspace",
		"$ignoreUnknownInstances": true,
		"$path": "assets/Workspace",

		"$properties": {
			"StreamingEnabled": false
		}
	},

    "Lighting": {
      "$properties": {
        "Ambient": [
          0,
          0,
          0
        ],
        "Brightness": 2,
        "GlobalShadows": true,
        "Outlines": false,
        "Technology": "Voxel"
      }
    },
    "SoundService": {
      "$properties": {
        "RespectFilteringEnabled": true
      }
    }
  }
}